indis/__init__.py
indis/__main__.py
indis/configuration.py
indis/logging.py
indis/output_factory.py
indis/source_factory.py
indis/cache/__init__.py
indis/cache/cache.py
indis/model/__init__.py
indis/model/basic_attributes.py
indis/model/command.py
indis/model/common.py
indis/model/dependency.py
indis/model/endpoint.py
indis/model/group.py
indis/model/host.py
indis/model/host_dependency.py
indis/model/notification.py
indis/model/service.py
indis/model/service_dependency.py
indis/model/timeperiod.py
indis/model/user.py
indis/model/usergroup.py
indis/model/zone.py
indis/output/__init__.py
indis/output/api_writer.py
indis/output/json_writer.py
indis/output/output_writer.py
indis/processor/__init__.py
indis/processor/common.py
indis/processor/groups.py
indis/processor/vars.py
indis/provider/__init__.py
indis/provider/source.py
indis/provider/source_reader.py
indis/provider/transfer.py
tests/__init__.py
tests/test_basic.py
indis-0.1.0.dist-info/COPYING
indis-0.1.0.dist-info/LICENSE
indis-0.1.0.dist-info/METADATA
indis-0.1.0.dist-info/WHEEL
indis-0.1.0.dist-info/top_level.txt
indis-0.1.0.dist-info/RECORD
